sequelframe/__init__.py
sequelframe/sequelframe.py
sequelframe-0.3.5.dist-info/LICENSE
sequelframe-0.3.5.dist-info/METADATA
sequelframe-0.3.5.dist-info/WHEEL
sequelframe-0.3.5.dist-info/top_level.txt
sequelframe-0.3.5.dist-info/RECORD
