Metadata-Version: 2.1
Name: sequelframe
Version: 0.3.5
Summary: SQL interface for CSV and Excel data using SQLite. Code available: https://github.com/Sinamirshahi/sequelframe
Author: Sina Mirshahi
Author-email: sina7th@gmail.com
Classifier: Programming Language :: Python :: 3
Classifier: License :: OSI Approved :: MIT License
Classifier: Operating System :: OS Independent
License-File: LICENSE
Requires-Dist: pandas
